entropy_hash/__init__.py
entropy_hash/benchmark/__init__.py
entropy_hash/benchmark/synthetic_bench.py
entropy_hash/model/__init__.py
entropy_hash/model/model.py
entropy_hash/pipeline/__init__.py
entropy_hash/pipeline/pipeline.py
entropy_hash/simhash/__init__.py
entropy_hash/simhash/simhash_c.py
entropy_hash/simhash/simhash_py.py
entropy_hash/simhash/simhash/__init__.py
entropy_hash/util/__init__.py
entropy_hash/util/hashing.py
entropy_hash/util/rand_docs.py
entropy_hash/util/transform.py
entropy_hash-0.1.3.dist-info/licenses/LICENSE
entropy_hash-0.1.3.dist-info/METADATA
entropy_hash-0.1.3.dist-info/WHEEL
entropy_hash-0.1.3.dist-info/top_level.txt
entropy_hash-0.1.3.dist-info/RECORD
