Metadata-Version: 2.4
Name: entropy-hash
Version: 0.1.3
Summary: EntropyHash: near document duplicate detection algorithm
Author-email: Saeed Dehqan <saeeddhqan@gmail.com>
License:                                  Apache License
Project-URL: Homepage, https://github.com/saeeddhqan/entropy_hash
Requires-Python: >=3.11
License-File: LICENSE
Requires-Dist: torch
Requires-Dist: numpy
Requires-Dist: scikit-learn
Dynamic: license-file
